nbqa/__init__.py
nbqa/__main__.py
nbqa/cmdline.py
nbqa/find_root.py
nbqa/handle_magics.py
nbqa/notebook_info.py
nbqa/optional.py
nbqa/output_parser.py
nbqa/path_utils.py
nbqa/replace_source.py
nbqa/save_code_source.py
nbqa/save_markdown_source.py
nbqa/text.py
nbqa/config/__init__.py
nbqa/config/config.py
nbqa-1.9.1.dist-info/LICENSE
nbqa-1.9.1.dist-info/METADATA
nbqa-1.9.1.dist-info/WHEEL
nbqa-1.9.1.dist-info/entry_points.txt
nbqa-1.9.1.dist-info/top_level.txt
nbqa-1.9.1.dist-info/RECORD
