Metadata-Version: 2.1
Name: nbqa
Version: 1.9.1
Summary: Run any standard Python code quality tool on a Jupyter Notebook
Home-page: https://github.com/nbQA-dev/nbQA
Author: Marco Gorelli, Girish Pasupathy, Sebastian Weigand
License: MIT
Project-URL: Documentation, https://nbQA.readthedocs.io/en/latest/
Project-URL: Source, https://github.com/nbQA-dev/nbQA
Project-URL: Tracker, https://github.com/nbQA-dev/nbQA/issues
Keywords: jupyter,notebook,format,lint
Classifier: Development Status :: 4 - Beta
Classifier: Environment :: Console
Classifier: Framework :: Jupyter
Classifier: Intended Audience :: Developers
Classifier: License :: OSI Approved :: MIT License
Classifier: Natural Language :: English
Classifier: Operating System :: OS Independent
Classifier: Programming Language :: Python :: 3
Classifier: Programming Language :: Python :: 3 :: Only
Classifier: Topic :: Software Development :: Quality Assurance
Requires-Python: >=3.9
License-File: LICENSE
Requires-Dist: autopep8>=1.5
Requires-Dist: ipython>=7.8.0
Requires-Dist: tokenize-rt>=3.2.0
Requires-Dist: tomli
Provides-Extra: toolchain
Requires-Dist: black; extra == "toolchain"
Requires-Dist: blacken-docs; extra == "toolchain"
Requires-Dist: flake8; extra == "toolchain"
Requires-Dist: isort; extra == "toolchain"
Requires-Dist: jupytext; extra == "toolchain"
Requires-Dist: mypy; extra == "toolchain"
Requires-Dist: pylint; extra == "toolchain"
Requires-Dist: pyupgrade; extra == "toolchain"
Requires-Dist: ruff; extra == "toolchain"
